event_bus/__init__.py
event_bus/bus.py
event_bus/exceptions.py
event_bus_async/__init__.py
event_bus_async/bus.py
event_bus_async/exceptions.py
event_bus_async-2.0.5.dist-info/LICENSE
event_bus_async-2.0.5.dist-info/METADATA
event_bus_async-2.0.5.dist-info/WHEEL
event_bus_async-2.0.5.dist-info/top_level.txt
event_bus_async-2.0.5.dist-info/RECORD
